[{"rank":"1","city":"新宿","total":746293},{"rank":"2","city":"池袋","total":565940},{"rank":"3","city":"渋谷","total":423037},{"rank":"4","city":"横浜","total":379053},{"rank":"5","city":"東京","total":369025},{"rank":"6","city":"品川","total":283705},{"rank":"7","city":"新橋","total":230477},{"rank":"8","city":"大宮","total":227683},{"rank":"9","city":"高田馬場","total":206915},{"rank":"10","city":"上野","total":186401},{"rank":"11","city":"北千住","total":179339},{"rank":"12","city":"川崎","total":157953},{"rank":"13","city":"有楽町","total":151848},{"rank":"14","city":"立川","total":145697},{"rank":"15","city":"田町","total":145215},{"rank":"16","city":"柏","total":145196},{"rank":"17","city":"浜松町","total":142956},{"rank":"18","city":"秋葉原","total":142517},{"rank":"19","city":"吉祥寺","total":139209},{"rank":"20","city":"船橋","total":131702},{"rank":"21","city":"蒲田","total":128892},{"rank":"22","city":"五反田","total":126269},{"rank":"23","city":"恵比寿","total":125839},{"rank":"24","city":"中野","total":114459},{"rank":"25","city":"御茶ノ水","total":111870},{"rank":"26","city":"神田","total":107156},{"rank":"27","city":"町田","total":105932},{"rank":"28","city":"西船橋","total":105895},{"rank":"29","city":"津田沼","total":105221},{"rank":"30","city":"千葉","total":104748},{"rank":"31","city":"国分寺","total":103226},{"rank":"32","city":"松戸","total":103126},{"rank":"33","city":"戸塚","total":100374},{"rank":"34","city":"目黒","total":98561},{"rank":"35","city":"藤沢","total":93411},{"rank":"36","city":"大森","total":90426},{"rank":"37","city":"西日暮里","total":90236},{"rank":"38","city":"錦糸町","total":88934},{"rank":"39","city":"飯田橋","total":88453},{"rank":"40","city":"水道橋","total":87238},{"rank":"41","city":"四ツ谷","total":86505},{"rank":"42","city":"大船","total":85190},{"rank":"43","city":"赤羽","total":85083},{"rank":"44","city":"三鷹","total":84410},{"rank":"45","city":"大井町","total":84052},{"rank":"46","city":"荻窪","total":82953},{"rank":"47","city":"八王子","total":81273},{"rank":"48","city":"御徒町","total":79824},{"rank":"49","city":"日暮里","total":79694},{"rank":"50","city":"大崎","total":79231},{"rank":"51","city":"鶴見","total":76360},{"rank":"52","city":"巣鴨","total":76311},{"rank":"53","city":"仙台","total":76001},{"rank":"54","city":"川口","total":74777},{"rank":"55","city":"浦和","total":74293},{"rank":"56","city":"原宿","total":72400},{"rank":"57","city":"桜木町","total":71076},{"rank":"58","city":"新小岩","total":68770},{"rank":"59","city":"武蔵溝ノ口","total":68666},{"rank":"60","city":"武蔵小杉","total":68632},{"rank":"61","city":"登戸","total":67257},{"rank":"62","city":"代々木","total":66650},{"rank":"63","city":"小岩","total":64690},{"rank":"64","city":"舞浜","total":62812},{"rank":"65","city":"王子","total":60811},{"rank":"66","city":"関内","total":60479},{"rank":"67","city":"南越谷","total":60341},{"rank":"68","city":"武蔵境","total":58717},{"rank":"69","city":"市ケ谷","total":58551},{"rank":"70","city":"蕨","total":58083},{"rank":"71","city":"市川","total":57694},{"rank":"72","city":"北朝霞","total":57581},{"rank":"73","city":"平塚","total":57393},{"rank":"74","city":"本八幡","total":56938},{"rank":"75","city":"南浦和","total":55467},{"rank":"76","city":"浅草橋","total":55414},{"rank":"77","city":"武蔵小金井","total":55281},{"rank":"78","city":"国立","total":55245},{"rank":"79","city":"大塚","total":54532},{"rank":"80","city":"亀戸","total":54477},{"rank":"81","city":"茅ケ崎","total":53360},{"rank":"82","city":"西川口","total":52905},{"rank":"83","city":"長津田","total":52889},{"rank":"84","city":"新木場","total":52625},{"rank":"85","city":"橋本","total":52261},{"rank":"86","city":"東戸塚","total":52179},{"rank":"87","city":"稲毛","total":50172},{"rank":"88","city":"北浦和","total":50030},{"rank":"89","city":"高円寺","total":49450},{"rank":"90","city":"新浦安","total":47738},{"rank":"91","city":"新横浜","total":47074},{"rank":"92","city":"辻堂","total":45157},{"rank":"93","city":"取手","total":44623},{"rank":"94","city":"駒込","total":44482},{"rank":"95","city":"阿佐ケ谷","total":44204},{"rank":"96","city":"菊名","total":43941},{"rank":"97","city":"海浜幕張","total":43662},{"rank":"98","city":"金町","total":42973},{"rank":"99","city":"石川町","total":41164},{"rank":"100","city":"上尾","total":41106}]